favitech/__init__.py
favitech/__main__.py
favitech/fingerprints.py
favitech/version.py
favitech-0.0.1.dist-info/LICENSE
favitech-0.0.1.dist-info/METADATA
favitech-0.0.1.dist-info/WHEEL
favitech-0.0.1.dist-info/entry_points.txt
favitech-0.0.1.dist-info/top_level.txt
favitech-0.0.1.dist-info/RECORD
