Metadata-Version: 2.1
Name: favitech
Version: 0.0.1
Summary: Detect web technologies based on favicons
Home-page: https://gitlab.com/Zer1t0/favitech
Author: Eloy Pérez González
Classifier: Programming Language :: Python :: 3
Classifier: License :: OSI Approved :: GNU General Public License v3 (GPLv3)
License-File: LICENSE
Requires-Dist: mmh3 ==2.5.1
Requires-Dist: requests
Requires-Dist: bs4
